magnet_pinn/__init__.py
magnet_pinn/data/__init__.py
magnet_pinn/data/_base.py
magnet_pinn/data/dataitem.py
magnet_pinn/data/grid.py
magnet_pinn/data/point.py
magnet_pinn/data/transforms.py
magnet_pinn/data/utils.py
magnet_pinn/generator/__init__.py
magnet_pinn/generator/__main__.py
magnet_pinn/generator/cli/__init__.py
magnet_pinn/generator/cli/cli.py
magnet_pinn/generator/cli/helpers.py
magnet_pinn/generator/io.py
magnet_pinn/generator/phantoms.py
magnet_pinn/generator/samplers.py
magnet_pinn/generator/serializers.py
magnet_pinn/generator/structures.py
magnet_pinn/generator/transforms.py
magnet_pinn/generator/typing.py
magnet_pinn/generator/utils.py
magnet_pinn/losses/__init__.py
magnet_pinn/losses/base.py
magnet_pinn/losses/physics.py
magnet_pinn/losses/utils.py
magnet_pinn/models/__init__.py
magnet_pinn/models/_unet3d/buildingblocks.py
magnet_pinn/models/_unet3d/models.py
magnet_pinn/models/_unet3d/se.py
magnet_pinn/models/_unet3d/utils.py
magnet_pinn/preprocessing/__init__.py
magnet_pinn/preprocessing/__main__.py
magnet_pinn/preprocessing/cli/__init__.py
magnet_pinn/preprocessing/cli/cli.py
magnet_pinn/preprocessing/cli/helpers.py
magnet_pinn/preprocessing/preprocessing.py
magnet_pinn/preprocessing/reading_field.py
magnet_pinn/preprocessing/reading_properties.py
magnet_pinn/preprocessing/simulation.py
magnet_pinn/preprocessing/virtual_directory.py
magnet_pinn/preprocessing/voxelizing_mesh.py
magnet_pinn/utils/__init__.py
magnet_pinn/utils/_normalization.py
magnet_pinn/utils/_perlin_noise.py
magnet_pinn-0.0.11.dist-info/LICENSE
magnet_pinn-0.0.11.dist-info/METADATA
magnet_pinn-0.0.11.dist-info/WHEEL
magnet_pinn-0.0.11.dist-info/RECORD
