Metadata-Version: 2.3
Name: magnet-pinn
Version: 0.0.11
Summary: This is the software package for simulating EM Fields using NNs
License: MIT
Author: Andrzej Dulny
Author-email: andzej.dulny@gmail.com
Requires-Python: >=3.11,<3.14
Classifier: License :: OSI Approved :: MIT License
Classifier: Programming Language :: Python :: 3
Classifier: Programming Language :: Python :: 3.11
Classifier: Programming Language :: Python :: 3.12
Classifier: Programming Language :: Python :: 3.13
Provides-Extra: linters
Requires-Dist: einops (>=0.8.0,<0.9.0)
Requires-Dist: findiff (>=0.10.2,<0.11.0)
Requires-Dist: h5py (>=3.10.0,<4.0.0)
Requires-Dist: libigl (>=2.6.1,<3.0.0)
Requires-Dist: manifold3d (>=3.1.0,<4.0.0)
Requires-Dist: mypy (>=1.9.0,<2.0.0) ; extra == "linters"
Requires-Dist: natsort (>=8.4.0,<9.0.0)
Requires-Dist: numpy (>=1.26.4)
Requires-Dist: ordered-set (>=4.1.0,<5.0.0)
Requires-Dist: pandas (>=2.2.2,<3.0.0)
Requires-Dist: rtree (>=1.2.0,<2.0.0)
Requires-Dist: scipy (>=1.13.0,<2.0.0)
Requires-Dist: torch (>=2.3.1,<3.0.0)
Requires-Dist: tqdm (>=4.66.4,<5.0.0)
Requires-Dist: trimesh (>=4.2.4)
